pypowsybl/__init__.py
pypowsybl/_pypowsybl.cpython-310-darwin.so
pypowsybl/_pypowsybl.pyi
pypowsybl/libjniortools.dylib
pypowsybl/libmath.dylib
pypowsybl/libortools.9.dylib
pypowsybl/libpowsybl-cpp.dylib
pypowsybl/libpypowsybl-java.dylib
pypowsybl/py.typed
pypowsybl/dynamic/__init__.py
pypowsybl/dynamic/impl/__init__.py
pypowsybl/dynamic/impl/event_mapping.py
pypowsybl/dynamic/impl/model_mapping.py
pypowsybl/dynamic/impl/output_variable_mapping.py
pypowsybl/dynamic/impl/parameters.py
pypowsybl/dynamic/impl/simulation.py
pypowsybl/dynamic/impl/simulation_result.py
pypowsybl/flowdecomposition/__init__.py
pypowsybl/flowdecomposition/impl/__init__.py
pypowsybl/flowdecomposition/impl/flowdecomposition.py
pypowsybl/flowdecomposition/impl/parameters.py
pypowsybl/flowdecomposition/impl/util.py
pypowsybl/glsk/__init__.py
pypowsybl/glsk/impl/__init__.py
pypowsybl/glsk/impl/glsk_document.py
pypowsybl/glsk/impl/util.py
pypowsybl/grid2op/__init__.py
pypowsybl/grid2op/impl/__init__.py
pypowsybl/grid2op/impl/backend.py
pypowsybl/loadflow/__init__.py
pypowsybl/loadflow/impl/__init__.py
pypowsybl/loadflow/impl/component_result.py
pypowsybl/loadflow/impl/loadflow.py
pypowsybl/loadflow/impl/loadflow_results_future_wrapper.py
pypowsybl/loadflow/impl/parameters.py
pypowsybl/loadflow/impl/slack_bus_result.py
pypowsybl/loadflow/impl/util.py
pypowsybl/loadflow/impl/validation_parameters.py
pypowsybl/loadflow/impl/validation_result.py
pypowsybl/network/__init__.py
pypowsybl/network/impl/__init__.py
pypowsybl/network/impl/bus_breaker_topology.py
pypowsybl/network/impl/layout_parameters.py
pypowsybl/network/impl/nad_parameters.py
pypowsybl/network/impl/nad_profile.py
pypowsybl/network/impl/network.py
pypowsybl/network/impl/network_creation_util.py
pypowsybl/network/impl/network_element_modification_util.py
pypowsybl/network/impl/node_breaker_topology.py
pypowsybl/network/impl/pandapower_converter.py
pypowsybl/network/impl/perunit.py
pypowsybl/network/impl/sld_parameters.py
pypowsybl-1.14.0.dist-info/licenses/LICENSE
pypowsybl-1.14.0.dist-info/METADATA
pypowsybl-1.14.0.dist-info/WHEEL
pypowsybl-1.14.0.dist-info/top_level.txt
pypowsybl-1.14.0.dist-info/RECORD
