Metadata-Version: 2.4
Name: pypowsybl
Version: 1.14.0
Summary: A PowSyBl Python API
Home-page: https://github.com/powsybl/pypowsybl
Author: Geoffroy Jamgotchian
Author-email: geoffroy.jamgotchian@gmail.com
Classifier: Development Status :: 5 - Production/Stable
Classifier: Programming Language :: Python :: 3
Classifier: Programming Language :: Python :: 3 :: Only
Classifier: Programming Language :: Python :: 3.9
Classifier: Programming Language :: Python :: 3.10
Classifier: Programming Language :: Python :: 3.11
Classifier: Programming Language :: Python :: 3.12
Classifier: Programming Language :: Python :: 3.13
Classifier: Programming Language :: Python :: Implementation :: CPython
Classifier: License :: OSI Approved :: Mozilla Public License 2.0 (MPL 2.0)
Classifier: Operating System :: POSIX :: Linux
Classifier: Operating System :: MacOS
Classifier: Operating System :: Microsoft :: Windows
Requires-Python: >=3.9
License-File: LICENSE
Requires-Dist: prettytable>=2.0.0
Requires-Dist: pandas>=2.2.3
Requires-Dist: networkx
Provides-Extra: pandapower
Requires-Dist: pandapower>=2.14.11; python_version < "3.13" and extra == "pandapower"
Dynamic: license-file
